maff.py
maff-0.1.dist-info/DESCRIPTION.rst
maff-0.1.dist-info/METADATA
maff-0.1.dist-info/RECORD
maff-0.1.dist-info/WHEEL
maff-0.1.dist-info/metadata.json
maff-0.1.dist-info/top_level.txt
