Metadata-Version: 2.0
Name: maff
Version: 0.1
Summary: Python convenience functions that I wish were in the math module
Home-page: https://github.com/cosmologicon/maff
Author: Christopher Knight
Author-email: cosmologicon@gmail.com
License: UNKNOWN
Platform: UNKNOWN
Classifier: Development Status :: 5 - Production/Stable
Classifier: License :: OSI Approved :: BSD License
Classifier: Programming Language :: Python :: 2.7
Classifier: Programming Language :: Python :: 3
Classifier: Topic :: Scientific/Engineering :: Mathematics
